jMF2D/__init__.py
jMF2D/jMF2D.py
jMF2D/utils.py
jMF2D-1.1.0.dist-info/LICENSE
jMF2D-1.1.0.dist-info/METADATA
jMF2D-1.1.0.dist-info/WHEEL
jMF2D-1.1.0.dist-info/top_level.txt
jMF2D-1.1.0.dist-info/RECORD
